Metadata-Version: 2.1
Name: click-bash4.2-completion
Version: 0.1.0
Summary: Bash 4.2 completion support for Click 8.0.x
Home-page: UNKNOWN
Author: Egor Abramov
Author-email: coreegor@gmail.com
License: UNKNOWN
Download-URL: https://github.com/coreegor/click-bash4.2-completion/archive/refs/tags/0.1.0.tar.gz
Project-URL: Source, https://github.com/coreegor/click-bash4.2-completion
Platform: UNKNOWN
Classifier: License :: OSI Approved :: MIT License
Classifier: Programming Language :: Python :: 3.7
Requires-Python: >=3.7
